tkdeft/__init__.py
tkdeft/object.py
tkdeft/utility/__init__.py
tkdeft/utility/fonts.py
tkdeft/utility/segoe_font.ttf
tkdeft/windows/__init__.py
tkdeft/windows/canvas.py
tkdeft/windows/draw.py
tkdeft/windows/drawwidget.py
tkdeft-0.1.2.dist-info/METADATA
tkdeft-0.1.2.dist-info/WHEEL
tkdeft-0.1.2.dist-info/RECORD
