Metadata-Version: 2.3
Name: tkdeft
Version: 0.1.2
Summary: 使用tkinter+tksvg开发的现代化界面库
Author: XiangQinxi
Author-email: xiangqinxi@outlook.com
Requires-Python: >=3.7,<4.0
Classifier: Programming Language :: Python :: 3
Classifier: Programming Language :: Python :: 3.7
Classifier: Programming Language :: Python :: 3.8
Classifier: Programming Language :: Python :: 3.9
Classifier: Programming Language :: Python :: 3.10
Classifier: Programming Language :: Python :: 3.11
Classifier: Programming Language :: Python :: 3.12
Classifier: Programming Language :: Python :: 3.13
Requires-Dist: easydict (>=1.13,<2.0)
Requires-Dist: pillow (>=10.2.0,<11.0.0)
Requires-Dist: svgwrite (>=1.4.3,<2.0.0)
Requires-Dist: tkextrafont (>=0.6.3,<0.7.0)
Requires-Dist: tksvg (>=0.7.4,<0.8.0)
Project-URL: Documentation, https://tkdeft.netlify.app
